setup.py
MPBS/__init__.py
MPBS.egg-info/PKG-INFO
MPBS.egg-info/SOURCES.txt
MPBS.egg-info/dependency_links.txt
MPBS.egg-info/requires.txt
MPBS.egg-info/top_level.txt
MPBS/client/__init__.py
MPBS/client/mpbs.py
MPBS/core/__init__.py
MPBS/core/base.py
MPBS/core/broker.py
MPBS/core/exception.py
MPBS/core/utils.py
MPBS/examples/__init__.py
MPBS/examples/mpbs/__init__.py
MPBS/examples/mpbs/mpbs_broker.py
MPBS/examples/mpbs/mpbs_client.py
MPBS/examples/mpbs/mpbs_server.py