Metadata-Version: 1.0
Name: MPBS
Version: 0.0.3.7
Summary: zmq based MultiPublisher-Broker-multiSubscriber framework
Home-page: http://www.example.com
Author: kevin90116
Author-email: kevin90116@gmail.com
License: UNKNOWN
Platform: any
